LICENSE
texttools/__init__.py
texttools/format.py
texttools/half_width.py
texttools/py.typed
texttools/text.py
texttools/text_cycle.py
texttools/text_find.py
texttools/text_format.py
python_texttools-0.0.5.dist-info/LICENSE
python_texttools-0.0.5.dist-info/METADATA
python_texttools-0.0.5.dist-info/WHEEL
python_texttools-0.0.5.dist-info/RECORD
